{"PublicacionSimilarCercana": null, "Banners": [], "Usuario": {"IngresoUsuario": null, "IngresoRegistroUsuario": null, "IngresoRecuperarUsuario": null, "NombresApellido": "", "Nombres": null, "ApellidoMaterno": "", "ApellidoPaterno": "", "CorreoElectronico": "", "Rut": "", "Autenticado": false, "Telefono": 0, "IdCodigoAreaTelefono": 0, "CodigoAreaTelefono": 0, "IdComuna": 0, "IdRegion": 0, "Direccion": "", "Perfiles": [], "PerfilFamilias": []}, "IdUsuario": null, "TipoPropiedadText": "Departamento Nuevo en Venta", "OrdenProyecto": 2, "Data": {"Propiedad": {"Dormitorios": 1, "Banos": 1, "Entrega": "1 Semestre 2019", "Construye": "Almagro", "Arquitecto": "", "Logo": "2020010159516063258.jpg", "Aspectos": "", "Descripcion": "El edificio está equipado con hall de acceso de doble altura. El cuarto piso cuenta con un patio con juegos infantiles y máquinas de ejercicio, salón de niños, salones multiuso y gimnasio equipado. En el último piso cuenta con piscina y cinco quinchos. Control con cámaras de seguridad en todos los pisos.", "ComentarioPrecio": "Precios referenciales, confirmar en sala de ventas de la inmobiliaria.", "ComentarioDormitorio": "", "ComentarioBano": "", "ComentarioServicio": "", "SalaVenta": {"Direccion": "General Mackenna 1555, Santiago Centro", "Horario": "", "Fono": "226713943 / 226963372", "Email": "ventas_generalmackenna@almagro.cl"}, "TiposPlanta": [{"Tipo": "26,01 m2", "Descripcion": "", "Nombre": "", "PrecioDesde": 1620.0, "Dormitorios": 1, "Banos": 1, "SuperficieTotal": 26.01, "SuperficieUtil": 26.01, "Orientacion": "", "Imagenes": ["n_wm_2016050230312861137.jpg"], "ImagenesSmall": ["s_wm_2016050230312861137.jpg"], "Propiedades": [], "HayAlgunaPublicada": false, "TextoPlantaSeleccion": "1 Dorm., 1 baño", "Identificador": "060a2147-6b77-4bd6-879d-fe71c1c85d2d"}, {"Tipo": "general mackenna planta 1", "Descripcion": "", "Nombre": "general mackenna planta 1", "PrecioDesde": 1790.0, "Dormitorios": 1, "Banos": 1, "SuperficieTotal": 26.01, "SuperficieUtil": 26.01, "Orientacion": "", "Imagenes": ["n_wm_2017011828516888212.jpg"], "ImagenesSmall": ["s_wm_2017011828516888212.jpg"], "Propiedades": [], "HayAlgunaPublicada": false, "TextoPlantaSeleccion": "1 Dorm., 1 baño", "Identificador": "2eebad4d-ce95-4cda-a14c-59661d828d7b"}, {"Tipo": "Depto. 26,01 M2 totales", "Descripcion": "<p class=\"des-bold\">Departamento:</p>\r\n\r\n<ul>\r\n \t<li>Superficie Útil: 26,0m²</li>\r\n \t<li class=\"des-bold\">TOTAL 26,01 m²</li>\r\n</ul>", "Nombre": "Depto. 26,01 M2 totales", "PrecioDesde": 1790.0, "Dormitorios": 1, "Banos": 1, "SuperficieTotal": 26.01, "SuperficieUtil": 26.01, "Orientacion": "", "Imagenes": ["n_wm_2017071748206301649.png"], "ImagenesSmall": ["s_wm_2017071748206301649.png"], "Propiedades": [], "HayAlgunaPublicada": false, "TextoPlantaSeleccion": "1 Dorm., 1 baño", "Identificador": "1aeb7c40-bec1-4ac3-a71f-2621164e77e4"}, {"Tipo": "Depto. 26,01 M2 totales", "Descripcion": "<p class=\"des-bold\">Departamento:</p>\r\n\r\n<ul>\r\n \t<li>Superficie Útil: 26,0m²</li>\r\n \t<li class=\"des-bold\">TOTAL 26,01 m²</li>\r\n</ul>", "Nombre": "Depto. 26,01 M2 totales", "PrecioDesde": 1790.0, "Dormitorios": 1, "Banos": 1, "SuperficieTotal": 26.01, "SuperficieUtil": 26.01, "Orientacion": "", "Imagenes": [], "ImagenesSmall": [], "Propiedades": [], "HayAlgunaPublicada": false, "TextoPlantaSeleccion": "1 Dorm., 1 baño", "Identificador": "b8e0ae69-5015-4b2e-9ac4-eafcd133ba6b"}, {"Tipo": "Depto. 26,01 M2 totales", "Descripcion": "<p class=\"des-bold\">Departamento:</p>\r\n\r\n<ul>\r\n \t<li>Superficie Útil: 26,0m²</li>\r\n \t<li class=\"des-bold\">TOTAL 26,01 m²</li>\r\n</ul>", "Nombre": "Depto. 26,01 M2 totales", "PrecioDesde": 1790.0, "Dormitorios": 1, "Banos": 1, "SuperficieTotal": 26.01, "SuperficieUtil": 26.01, "Orientacion": "", "Imagenes": ["n_wm_2017121844185739109.png", "n_wm_2018010247426505601.png"], "ImagenesSmall": ["s_wm_2017121844185739109.png", "s_wm_2018010247426505601.png"], "Propiedades": [{"Nombre": "Depto. 26,01 M2 totales", "NumeroPropiedad": "Depto. 26,01 M2 totales", "NumeroPiso": 0, "MetrosTotales": "26,01", "MetrosUtiles": "26,01", "Precio": 2235.0, "Orientacion": "", "Descripcion": "<p class=\"des-bold\">Departamento:</p>\r\n\r\n<ul>\r\n \t<li>Superficie Útil: 26,0m²</li>\r\n \t<li class=\"des-bold\">TOTAL 26,01 m²</li>\r\n</ul>", "Dormitorios": 1, "Banos": 1, "EstaPublicado": true, "Identificador": "e0e124e0-3362-4b99-8d3f-968b82648171"}], "HayAlgunaPublicada": true, "TextoPlantaSeleccion": "1 Dorm., 1 baño", "Identificador": "fcde7cde-4732-4973-8b60-a1837c530de7"}, {"Tipo": "35 m2", "Descripcion": "", "Nombre": "", "PrecioDesde": 2160.0, "Dormitorios": 1, "Banos": 1, "SuperficieTotal": 35.0, "SuperficieUtil": 32.18, "Orientacion": "", "Imagenes": ["n_wm_2016050233075713645.jpg"], "ImagenesSmall": ["s_wm_2016050233075713645.jpg"], "Propiedades": [], "HayAlgunaPublicada": false, "TextoPlantaSeleccion": "1 Dorm., 1 baño", "Identificador": "8ebf4171-d59e-4d8a-abad-c3aa6fcd19cd"}, {"Tipo": "general mackenna planta 3 A", "Descripcion": "", "Nombre": "general mackenna planta 3 A", "PrecioDesde": 2440.0, "Dormitorios": 1, "Banos": 1, "SuperficieTotal": 36.69, "SuperficieUtil": 33.93, "Orientacion": "", "Imagenes": ["n_wm_2017061555234782915.jpg"], "ImagenesSmall": ["s_wm_2017061555234782915.jpg"], "Propiedades": [], "HayAlgunaPublicada": false, "TextoPlantaSeleccion": "1 Dorm., 1 baño", "Identificador": "5054e873-8ea9-4fc3-be05-f073dd187647"}, {"Tipo": "Depto. 35,00 M2 totales", "Descripcion": "<p class=\"des-bold\">Departamento:</p>\r\n\r\n<ul>\r\n \t<li>Superficie Útil: 32,18 m²</li>\r\n \t<li>Terraza: 2,82 m²</li>\r\n \t<li class=\"des-bold\">TOTAL 35,00 m²</li>\r\n</ul>", "Nombre": "Depto. 35,00 M2 totales", "PrecioDesde": 2440.0, "Dormitorios": 1, "Banos": 1, "SuperficieTotal": 35.0, "SuperficieUtil": 32.18, "Orientacion": "", "Imagenes": ["n_wm_2017071748234625600.png"], "ImagenesSmall": ["s_wm_2017071748234625600.png"], "Propiedades": [], "HayAlgunaPublicada": false, "TextoPlantaSeleccion": "1 Dorm., 1 baño", "Identificador": "961034f4-22e5-4c97-ae8e-ca78624e2c06"}, {"Tipo": "Depto. 35,00 M2 totales", "Descripcion": "<p class=\"des-bold\">Departamento:</p>\r\n\r\n<ul>\r\n \t<li>Superficie Útil: 32,18 m²</li>\r\n \t<li>Terraza: 2,82 m²</li>\r\n \t<li class=\"des-bold\">TOTAL 35,00 m²</li>\r\n</ul>", "Nombre": "Depto. 35,00 M2 totales", "PrecioDesde": 2440.0, "Dormitorios": 1, "Banos": 1, "SuperficieTotal": 35.0, "SuperficieUtil": 32.18, "Orientacion": "", "Imagenes": [], "ImagenesSmall": [], "Propiedades": [], "HayAlgunaPublicada": false, "TextoPlantaSeleccion": "1 Dorm., 1 baño", "Identificador": "3ef657f7-39e1-4da3-a0aa-ee5ada028e63"}, {"Tipo": "Depto. 35,00 M2 totales", "Descripcion": "<p class=\"des-bold\">Departamento:</p>\r\n\r\n<ul>\r\n \t<li>Superficie Útil: 32,18 m²</li>\r\n \t<li>Terraza: 2,82 m²</li>\r\n \t<li class=\"des-bold\">TOTAL 35,00 m²</li>\r\n</ul>", "Nombre": "Depto. 35,00 M2 totales", "PrecioDesde": 2440.0, "Dormitorios": 1, "Banos": 1, "SuperficieTotal": 35.0, "SuperficieUtil": 32.18, "Orientacion": "", "Imagenes": ["n_wm_2017121844207603116.png", "n_wm_2018010247444998310.png"], "ImagenesSmall": ["s_wm_2017121844207603116.png", "s_wm_2018010247444998310.png"], "Propiedades": [{"Nombre": "Depto. 35,00 M2 totales", "NumeroPropiedad": "Depto. 35,00 M2 totales", "NumeroPiso": 0, "MetrosTotales": "35", "MetrosUtiles": "32,18", "Precio": 3255.0, "Orientacion": "", "Descripcion": "<p class=\"des-bold\">Departamento:</p>\r\n\r\n<ul>\r\n \t<li>Superficie Útil: 32,18 m²</li>\r\n \t<li>Terraza: 2,82 m²</li>\r\n \t<li class=\"des-bold\">TOTAL 35,00 m²</li>\r\n</ul>", "Dormitorios": 1, "Banos": 1, "EstaPublicado": true, "Identificador": "92d2a656-26db-4846-8e43-593f2e7d5b76"}], "HayAlgunaPublicada": true, "TextoPlantaSeleccion": "1 Dorm., 1 baño", "Identificador": "14ab9835-1dcc-4dfa-b398-ff14e6527d20"}, {"Tipo": "general mackenna planta 2", "Descripcion": "", "Nombre": "general mackenna planta 2", "PrecioDesde": 2480.0, "Dormitorios": 1, "Banos": 1, "SuperficieTotal": 35.0, "SuperficieUtil": 32.18, "Orientacion": "", "Imagenes": ["n_wm_2017011828575407146.jpg"], "ImagenesSmall": ["s_wm_2017011828575407146.jpg"], "Propiedades": [], "HayAlgunaPublicada": false, "TextoPlantaSeleccion": "1 Dorm., 1 baño", "Identificador": "e40be7ae-0f52-438f-9554-7345e95214e3"}, {"Tipo": "48,37 m2", "Descripcion": "", "Nombre": "", "PrecioDesde": 2560.0, "Dormitorios": 2, "Banos": 1, "SuperficieTotal": 48.37, "SuperficieUtil": 43.05, "Orientacion": "", "Imagenes": ["n_wm_2016050242256169001.jpg"], "ImagenesSmall": ["s_wm_2016050242256169001.jpg"], "Propiedades": [], "HayAlgunaPublicada": false, "TextoPlantaSeleccion": "2 Dorm., 1 baño", "Identificador": "de166e45-0897-478a-9bad-1c3cdd09d6fd"}, {"Tipo": "48,24 m2", "Descripcion": "", "Nombre": "", "PrecioDesde": 2670.0, "Dormitorios": 2, "Banos": 1, "SuperficieTotal": 48.24, "SuperficieUtil": 40.82, "Orientacion": "", "Imagenes": ["n_wm_2016050239379563581.jpg"], "ImagenesSmall": ["s_wm_2016050239379563581.jpg"], "Propiedades": [], "HayAlgunaPublicada": false, "TextoPlantaSeleccion": "2 Dorm., 1 baño", "Identificador": "f8d4cd1d-25a3-4d28-bd6c-6cd79b66c663"}, {"Tipo": "Depto. 36,13 mts2 totales", "Descripcion": "<p class=\"des-bold\">Departamento:</p>\r\n\r\n<ul>\r\n \t<li>Superficie Útil: 33,31 m²</li>\r\n \t<li>Terraza: 2,82 m²</li>\r\n \t<li class=\"des-bold\">TOTAL 36,13 m²</li>\r\n</ul>", "Nombre": "Depto. 36,13 mts2 totales", "PrecioDesde": 2720.0, "Dormitorios": 1, "Banos": 1, "SuperficieTotal": 36.13, "SuperficieUtil": 33.31, "Orientacion": "", "Imagenes": ["n_wm_2018053143034148948.png"], "ImagenesSmall": ["s_wm_2018053143034148948.png"], "Propiedades": [], "HayAlgunaPublicada": false, "TextoPlantaSeleccion": "1 Dorm., 1 baño", "Identificador": "c36510fc-3a40-4de4-8dac-66136a0d878b"}, {"Tipo": "general mackenna planta 3", "Descripcion": "", "Nombre": "general mackenna planta 3", "PrecioDesde": 2770.0, "Dormitorios": 2, "Banos": 1, "SuperficieTotal": 48.41, "SuperficieUtil": 43.05, "Orientacion": "", "Imagenes": ["n_wm_2017011829172497660.jpg"], "ImagenesSmall": ["s_wm_2017011829172497660.jpg"], "Propiedades": [], "HayAlgunaPublicada": false, "TextoPlantaSeleccion": "2 Dorm., 1 baño", "Identificador": "cf240606-34e1-4c3b-80df-f818ccb7d344"}, {"Tipo": "Depto. 48,41 M2 totales", "Descripcion": "<p class=\"des-bold\">Departamento:</p>\r\n\r\n<ul>\r\n \t<li>Superficie Útil: 43,05 m²</li>\r\n \t<li>Terraza: 5,36 m²</li>\r\n \t<li class=\"des-bold\">TOTAL 48,41 m²</li>\r\n</ul>", "Nombre": "Depto. 48,41 M2 totales", "PrecioDesde": 2770.0, "Dormitorios": 2, "Banos": 1, "SuperficieTotal": 48.41, "SuperficieUtil": 43.05, "Orientacion": "", "Imagenes": ["n_wm_2017071748185188657.png"], "ImagenesSmall": ["s_wm_2017071748185188657.png"], "Propiedades": [], "HayAlgunaPublicada": false, "TextoPlantaSeleccion": "2 Dorm., 1 baño", "Identificador": "09fb7837-096c-4818-a337-20b60803a5e5"}, {"Tipo": "Depto. 48,41 M2 totales", "Descripcion": "<p class=\"des-bold\">Departamento:</p>\r\n\r\n<ul>\r\n \t<li>Superficie Útil: 43,05 m²</li>\r\n \t<li>Terraza: 5,36 m²</li>\r\n \t<li class=\"des-bold\">TOTAL 48,41 m²</li>\r\n</ul>", "Nombre": "Depto. 48,41 M2 totales", "PrecioDesde": 2770.0, "Dormitorios": 2, "Banos": 1, "SuperficieTotal": 48.41, "SuperficieUtil": 43.05, "Orientacion": "", "Imagenes": [], "ImagenesSmall": [], "Propiedades": [], "HayAlgunaPublicada": false, "TextoPlantaSeleccion": "2 Dorm., 1 baño", "Identificador": "0a5a667f-6778-47d3-86e8-f5a53c9c06d4"}, {"Tipo": "Depto. 48,41 M2 totales", "Descripcion": "<p class=\"des-bold\">Departamento:</p>\r\n\r\n<ul>\r\n \t<li>Superficie Útil: 43,05 m²</li>\r\n \t<li>Terraza: 5,36 m²</li>\r\n \t<li class=\"des-bold\">TOTAL 48,41 m²</li>\r\n</ul>", "Nombre": "Depto. 48,41 M2 totales", "PrecioDesde": 2770.0, "Dormitorios": 2, "Banos": 1, "SuperficieTotal": 48.41, "SuperficieUtil": 43.05, "Orientacion": "", "Imagenes": ["n_wm_2017121844166796245.png", "n_wm_2018010247410043192.png"], "ImagenesSmall": ["s_wm_2017121844166796245.png", "s_wm_2018010247410043192.png"], "Propiedades": [], "HayAlgunaPublicada": false, "TextoPlantaSeleccion": "2 Dorm., 1 baño", "Identificador": "05603782-fc76-4451-8839-43767a61012c"}, {"Tipo": "52,39 m2", "Descripcion": "", "Nombre": "", "PrecioDesde": 2830.0, "Dormitorios": 2, "Banos": 2, "SuperficieTotal": 52.39, "SuperficieUtil": 50.05, "Orientacion": "", "Imagenes": ["n_wm_2016050246442328955.jpg"], "ImagenesSmall": ["s_wm_2016050246442328955.jpg"], "Propiedades": [], "HayAlgunaPublicada": false, "TextoPlantaSeleccion": "2 Dorm., 2 baños", "Identificador": "81314e7d-a2c2-4b9b-9711-f77289e9a100"}, {"Tipo": "53,96 m2", "Descripcion": "", "Nombre": "", "PrecioDesde": 2900.0, "Dormitorios": 2, "Banos": 2, "SuperficieTotal": 53.96, "SuperficieUtil": 51.18, "Orientacion": "", "Imagenes": ["n_wm_2016050248544393537.jpg"], "ImagenesSmall": ["s_wm_2016050248544393537.jpg"], "Propiedades": [], "HayAlgunaPublicada": false, "TextoPlantaSeleccion": "2 Dorm., 2 baños", "Identificador": "58dd6521-63b5-4d38-82b5-0ef5da4cbc46"}, {"Tipo": "51,73 m2", "Descripcion": "", "Nombre": "", "PrecioDesde": 2910.0, "Dormitorios": 2, "Banos": 2, "SuperficieTotal": 51.73, "SuperficieUtil": 48.73, "Orientacion": "", "Imagenes": ["n_wm_2016050244346827041.jpg"], "ImagenesSmall": ["s_wm_2016050244346827041.jpg"], "Propiedades": [], "HayAlgunaPublicada": false, "TextoPlantaSeleccion": "2 Dorm., 2 baños", "Identificador": "475e4442-f2d8-4287-b9e5-2e0c496f459c"}, {"Tipo": "general mackenna planta 6", "Descripcion": "", "Nombre": "general mackenna planta 6", "PrecioDesde": 2910.0, "Dormitorios": 2, "Banos": 2, "SuperficieTotal": 51.73, "SuperficieUtil": 48.73, "Orientacion": "", "Imagenes": ["n_wm_2017011829061490365.jpg"], "ImagenesSmall": ["s_wm_2017011829061490365.jpg"], "Propiedades": [], "HayAlgunaPublicada": false, "TextoPlantaSeleccion": "2 Dorm., 2 baños", "Identificador": "aa38e84f-24e6-414b-8b63-a48eac97d0fc"}, {"Tipo": "Depto. 51,73 M2 totales", "Descripcion": "<p class=\"des-bold\">Departamento:</p>\r\n\r\n<ul>\r\n \t<li>Superficie Útil: 48,73 m²</li>\r\n \t<li>Terraza: 3 m²</li>\r\n \t<li class=\"des-bold\">TOTAL 51,73 m²</li>\r\n</ul>", "Nombre": "Depto. 51,73 M2 totales", "PrecioDesde": 2910.0, "Dormitorios": 2, "Banos": 1, "SuperficieTotal": 51.73, "SuperficieUtil": 48.73, "Orientacion": "", "Imagenes": ["n_wm_2017071748292473731.png"], "ImagenesSmall": ["s_wm_2017071748292473731.png"], "Propiedades": [], "HayAlgunaPublicada": false, "TextoPlantaSeleccion": "2 Dorm., 1 baño", "Identificador": "e1869af1-8d62-4c2e-b21b-973bbdb37be4"}, {"Tipo": "Depto. 51,73 M2 totales", "Descripcion": "<p class=\"des-bold\">Departamento:</p>\r\n\r\n<ul>\r\n \t<li>Superficie Útil: 48,73 m²</li>\r\n \t<li>Terraza: 3 m²</li>\r\n \t<li class=\"des-bold\">TOTAL 51,73 m²</li>\r\n</ul>", "Nombre": "Depto. 51,73 M2 totales", "PrecioDesde": 2910.0, "Dormitorios": 2, "Banos": 1, "SuperficieTotal": 51.73, "SuperficieUtil": 48.73, "Orientacion": "", "Imagenes": [], "ImagenesSmall": [], "Propiedades": [], "HayAlgunaPublicada": false, "TextoPlantaSeleccion": "2 Dorm., 1 baño", "Identificador": "7e197d49-e61b-4108-91bb-c47367e4d806"}, {"Tipo": "Depto. 51,73 M2 totales", "Descripcion": "<p class=\"des-bold\">Departamento:</p>\r\n\r\n<ul>\r\n \t<li>Superficie Útil: 48,73 m²</li>\r\n \t<li>Terraza: 3 m²</li>\r\n \t<li class=\"des-bold\">TOTAL 51,73 m²</li>\r\n</ul>", "Nombre": "Depto. 51,73 M2 totales", "PrecioDesde": 2910.0, "Dormitorios": 2, "Banos": 2, "SuperficieTotal": 51.73, "SuperficieUtil": 48.73, "Orientacion": "", "Imagenes": ["n_wm_2017121844255769820.png", "n_wm_2018010247492095210.png"], "ImagenesSmall": ["s_wm_2017121844255769820.png", "s_wm_2018010247492095210.png"], "Propiedades": [], "HayAlgunaPublicada": false, "TextoPlantaSeleccion": "2 Dorm., 2 baños", "Identificador": "cf6882ab-9bd4-4d00-9bfa-a11951b2527a"}, {"Tipo": "46,18 m2-Dúplex", "Descripcion": "", "Nombre": "", "PrecioDesde": 2970.0, "Dormitorios": 1, "Banos": 1, "SuperficieTotal": 46.18, "SuperficieUtil": 42.58, "Orientacion": "", "Imagenes": ["n_wm_2016050236264358303.jpg"], "ImagenesSmall": ["s_wm_2016050236264358303.jpg"], "Propiedades": [], "HayAlgunaPublicada": false, "TextoPlantaSeleccion": "1 Dorm., 1 baño", "Identificador": "8b8338f2-3b74-433c-828e-352c7f50bbf1"}, {"Tipo": "Dúplex General Mackenna 46,18 M2", "Descripcion": "<p class=\"des-bold\">Duplex:</p>\r\n\r\n<ul>\r\n \t<li>Superficie Útil: 42,58 m²</li>\r\n \t<li>Terraza: 3,6 m²</li>\r\n \t<li class=\"des-bold\">TOTAL 46,18 m²</li>\r\n</ul>", "Nombre": "Dúplex General Mackenna 46,18 M2", "PrecioDesde": 2980.0, "Dormitorios": 1, "Banos": 1, "SuperficieTotal": 46.18, "SuperficieUtil": 42.58, "Orientacion": "", "Imagenes": ["n_wm_2017121844120659118.png", "n_wm_2018010247347884141.png"], "ImagenesSmall": ["s_wm_2017121844120659118.png", "s_wm_2018010247347884141.png"], "Propiedades": [], "HayAlgunaPublicada": false, "TextoPlantaSeleccion": "1 Dorm., 1 baño", "Identificador": "cf57a964-fe8f-4ffb-89f4-9862d0efaf74"}, {"Tipo": "general mackenna planta 3.1", "Descripcion": "", "Nombre": "general mackenna planta 3.1", "PrecioDesde": 2990.0, "Dormitorios": 1, "Banos": 1, "SuperficieTotal": 46.18, "SuperficieUtil": 42.58, "Orientacion": "", "Imagenes": ["n_wm_2017011829013422953.jpg"], "ImagenesSmall": ["s_wm_2017011829013422953.jpg"], "Propiedades": [], "HayAlgunaPublicada": false, "TextoPlantaSeleccion": "1 Dorm., 1 baño", "Identificador": "74a6c6ea-f3e7-4fca-ae0c-85babb45f914"}, {"Tipo": "Dúplex General Mackenna 46,18 M2", "Descripcion": "<p class=\"des-bold\">Duplex: </p>\r\n\r\n<ul>\r\n \t<li>Superficie Útil: 42,58 m²</li>\t\t\r\n\t<li>Terraza: 3,6 m²</li>        \r\n \t<li class=\"des-bold\">TOTAL 46,18 m²</li>\r\n</ul>", "Nombre": "Dúplex General Mackenna 46,18 M2", "PrecioDesde": 2990.0, "Dormitorios": 1, "Banos": 1, "SuperficieTotal": 46.18, "SuperficieUtil": 42.58, "Orientacion": "", "Imagenes": ["n_wm_2017071748144122942.png"], "ImagenesSmall": ["s_wm_2017071748144122942.png"], "Propiedades": [], "HayAlgunaPublicada": false, "TextoPlantaSeleccion": "1 Dorm., 1 baño", "Identificador": "e346b502-3545-4446-b76c-39459d3a0ec3"}, {"Tipo": "Dúplex General Mackenna 46,18 M2", "Descripcion": "<p class=\"des-bold\">Duplex: </p>\r\n\r\n<ul>\r\n \t<li>Superficie Útil: 42,58 m²</li>\t\t\r\n\t<li>Terraza: 3,6 m²</li>        \r\n \t<li class=\"des-bold\">TOTAL 46,18 m²</li>\r\n</ul>", "Nombre": "Dúplex General Mackenna 46,18 M2", "PrecioDesde": 2990.0, "Dormitorios": 1, "Banos": 1, "SuperficieTotal": 46.18, "SuperficieUtil": 42.58, "Orientacion": "", "Imagenes": [], "ImagenesSmall": [], "Propiedades": [], "HayAlgunaPublicada": false, "TextoPlantaSeleccion": "1 Dorm., 1 baño", "Identificador": "db1204b9-538a-400c-84b9-4882b336d72b"}, {"Tipo": "59,88 m2", "Descripcion": "", "Nombre": "", "PrecioDesde": 3050.0, "Dormitorios": 2, "Banos": 2, "SuperficieTotal": 59.88, "SuperficieUtil": 54.52, "Orientacion": "", "Imagenes": ["n_wm_2016050251038801673.jpg"], "ImagenesSmall": ["s_wm_2016050251038801673.jpg"], "Propiedades": [], "HayAlgunaPublicada": false, "TextoPlantaSeleccion": "2 Dorm., 2 baños", "Identificador": "733d84cb-a813-489e-a670-59435677f5c6"}, {"Tipo": "general mackenna planta 7", "Descripcion": "", "Nombre": "general mackenna planta 7", "PrecioDesde": 3050.0, "Dormitorios": 2, "Banos": 2, "SuperficieTotal": 52.39, "SuperficieUtil": 50.05, "Orientacion": "", "Imagenes": ["n_wm_2017011829093485223.jpg"], "ImagenesSmall": ["s_wm_2017011829093485223.jpg"], "Propiedades": [], "HayAlgunaPublicada": false, "TextoPlantaSeleccion": "2 Dorm., 2 baños", "Identificador": "27068b3a-0fcf-4104-8e9f-eb2c1a2d3053"}, {"Tipo": "Depto. 52,39 M2 totales", "Descripcion": "<p class=\"des-bold\">Departamento:</p>\r\n\r\n<ul>\r\n \t<li>Superficie Útil: 50,05 m²</li>\r\n \t<li>Terraza: 2,34 m²</li>\r\n \t<li class=\"des-bold\">TOTAL 52,39 m²</li>\r\n</ul>", "Nombre": "Depto. 52,39 M2 totales", "PrecioDesde": 3050.0, "Dormitorios": 2, "Banos": 1, "SuperficieTotal": 52.39, "SuperficieUtil": 50.05, "Orientacion": "", "Imagenes": ["n_wm_2017071748322357880.png"], "ImagenesSmall": ["s_wm_2017071748322357880.png"], "Propiedades": [], "HayAlgunaPublicada": false, "TextoPlantaSeleccion": "2 Dorm., 1 baño", "Identificador": "e904a374-4ef8-459f-ba82-ee7fb80a8dbe"}, {"Tipo": "Depto. 52,39 M2 totales", "Descripcion": "<p class=\"des-bold\">Departamento:</p>\r\n\r\n<ul>\r\n \t<li>Superficie Útil: 50,05 m²</li>\r\n \t<li>Terraza: 2,34 m²</li>\r\n \t<li class=\"des-bold\">TOTAL 52,39 m²</li>\r\n</ul>", "Nombre": "Depto. 52,39 M2 totales", "PrecioDesde": 3050.0, "Dormitorios": 2, "Banos": 1, "SuperficieTotal": 52.39, "SuperficieUtil": 50.05, "Orientacion": "", "Imagenes": [], "ImagenesSmall": [], "Propiedades": [], "HayAlgunaPublicada": false, "TextoPlantaSeleccion": "2 Dorm., 1 baño", "Identificador": "cca35421-148b-4228-9ddb-c5c790fc4f90"}, {"Tipo": "Depto. 52,39 M2 totales", "Descripcion": "<p class=\"des-bold\">Departamento:</p>\r\n\r\n<ul>\r\n \t<li>Superficie Útil: 50,05 m²</li>\r\n \t<li>Terraza: 2,34 m²</li>\r\n \t<li class=\"des-bold\">TOTAL 52,39 m²</li>\r\n</ul>", "Nombre": "Depto. 52,39 M2 totales", "PrecioDesde": 3050.0, "Dormitorios": 2, "Banos": 2, "SuperficieTotal": 52.39, "SuperficieUtil": 50.05, "Orientacion": "", "Imagenes": ["n_wm_2017121844283674065.png", "n_wm_2018010247515678653.png"], "ImagenesSmall": ["s_wm_2017121844283674065.png", "s_wm_2018010247515678653.png"], "Propiedades": [], "HayAlgunaPublicada": false, "TextoPlantaSeleccion": "2 Dorm., 2 baños", "Identificador": "062bca77-6067-49b5-9982-cd0cdb7fce02"}, {"Tipo": "Depto. 48,24 M2 totales", "Descripcion": "<p class=\"des-bold\">Departamento:</p>\r\n\r\n<ul>\r\n \t<li>Superficie Útil: 40,82 m²</li>\r\n \t<li>Terraza: 7,42 m²</li>\r\n \t<li class=\"des-bold\">TOTAL 48,24 m²</li>\r\n</ul>", "Nombre": "Depto. 48,24 M2 totales", "PrecioDesde": 3050.0, "Dormitorios": 2, "Banos": 1, "SuperficieTotal": 48.24, "SuperficieUtil": 40.82, "Orientacion": "", "Imagenes": ["n_wm_2018053143059912214.png"], "ImagenesSmall": ["s_wm_2018053143059912214.png"], "Propiedades": [], "HayAlgunaPublicada": false, "TextoPlantaSeleccion": "2 Dorm., 1 baño", "Identificador": "31f9c1b8-405c-4136-91b7-c95a6141e99c"}, {"Tipo": "general mackenna planta 8", "Descripcion": "", "Nombre": "general mackenna planta 8", "PrecioDesde": 3060.0, "Dormitorios": 2, "Banos": 2, "SuperficieTotal": 52.38, "SuperficieUtil": 49.75, "Orientacion": "", "Imagenes": ["n_wm_2017011829119449137.jpg"], "ImagenesSmall": ["s_wm_2017011829119449137.jpg"], "Propiedades": [], "HayAlgunaPublicada": false, "TextoPlantaSeleccion": "2 Dorm., 2 baños", "Identificador": "8f8eafe7-4ae0-4752-938e-7abf87396cc3"}, {"Tipo": "Depto. 52,38 M2 totales", "Descripcion": "<p class=\"des-bold\">Departamento:</p>\r\n\r\n<ul>\r\n \t<li>Superficie Útil: 49,75 m²</li>\r\n \t<li>Terraza: 2,63 m²</li>\r\n \t<li class=\"des-bold\">TOTAL 52,38 m²</li>\r\n</ul>", "Nombre": "Depto. 52,38 M2 totales", "PrecioDesde": 3060.0, "Dormitorios": 2, "Banos": 1, "SuperficieTotal": 52.38, "SuperficieUtil": 49.75, "Orientacion": "", "Imagenes": ["n_wm_2017071748360363212.png"], "ImagenesSmall": ["s_wm_2017071748360363212.png"], "Propiedades": [], "HayAlgunaPublicada": false, "TextoPlantaSeleccion": "2 Dorm., 1 baño", "Identificador": "ad606192-ee31-46fd-a287-98f93fe59941"}, {"Tipo": "Depto. 52,38 M2 totales", "Descripcion": "<p class=\"des-bold\">Departamento:</p>\r\n\r\n<ul>\r\n \t<li>Superficie Útil: 49,75 m²</li>\r\n \t<li>Terraza: 2,63 m²</li>\r\n \t<li class=\"des-bold\">TOTAL 52,38 m²</li>\r\n</ul>", "Nombre": "Depto. 52,38 M2 totales", "PrecioDesde": 3060.0, "Dormitorios": 2, "Banos": 1, "SuperficieTotal": 52.38, "SuperficieUtil": 49.75, "Orientacion": "", "Imagenes": [], "ImagenesSmall": [], "Propiedades": [], "HayAlgunaPublicada": false, "TextoPlantaSeleccion": "2 Dorm., 1 baño", "Identificador": "541711c7-9fcf-495a-86dc-309488f7e564"}, {"Tipo": "Depto. 52,38 M2 totales", "Descripcion": "<p class=\"des-bold\">Departamento:</p>\r\n\r\n<ul>\r\n \t<li>Superficie Útil: 49,75 m²</li>\r\n \t<li>Terraza: 2,63 m²</li>\r\n \t<li class=\"des-bold\">TOTAL 51,48 m²</li>\r\n</ul>", "Nombre": "Depto. 52,38 M2 totales", "PrecioDesde": 3060.0, "Dormitorios": 2, "Banos": 2, "SuperficieTotal": 52.38, "SuperficieUtil": 49.75, "Orientacion": "", "Imagenes": ["n_wm_2017121844321629855.png", "n_wm_2018010247540152249.png"], "ImagenesSmall": ["s_wm_2017121844321629855.png", "s_wm_2018010247540152249.png"], "Propiedades": [], "HayAlgunaPublicada": false, "TextoPlantaSeleccion": "2 Dorm., 2 baños", "Identificador": "bb9d1404-119a-45a1-9333-b27155b14611"}, {"Tipo": "Depto. 51,48 M2 totales", "Descripcion": "<p class=\"des-bold\">Departamento:</p>\r\n\r\n<ul>\r\n \t<li>Superficie Útil: 48,85 m²</li>\r\n \t<li>Terraza: 2,63 m²</li>\r\n \t<li class=\"des-bold\">TOTAL 51,48 m²</li>\r\n</ul>", "Nombre": "Depto. 51,48 M2 totales", "PrecioDesde": 3275.0, "Dormitorios": 2, "Banos": 2, "SuperficieTotal": 51.48, "SuperficieUtil": 48.85, "Orientacion": "", "Imagenes": ["n_wm_2018062741128602277.png"], "ImagenesSmall": ["s_wm_2018062741128602277.png"], "Propiedades": [], "HayAlgunaPublicada": false, "TextoPlantaSeleccion": "2 Dorm., 2 baños", "Identificador": "dee922d4-23d9-4983-9754-5a1eff304e47"}, {"Tipo": "general mackenna planta 5", "Descripcion": "", "Nombre": "general mackenna planta 5", "PrecioDesde": 3340.0, "Dormitorios": 2, "Banos": 2, "SuperficieTotal": 59.88, "SuperficieUtil": 54.52, "Orientacion": "", "Imagenes": ["n_wm_2017011829207912711.jpg"], "ImagenesSmall": ["s_wm_2017011829207912711.jpg"], "Propiedades": [], "HayAlgunaPublicada": false, "TextoPlantaSeleccion": "2 Dorm., 2 baños", "Identificador": "16daf8a1-e6a2-48bd-be5a-f51eaeb5a766"}, {"Tipo": "Depto. 59,88 M2 totales", "Descripcion": "<p class=\"des-bold\">Departamento:</p>\r\n\r\n<ul>\r\n \t<li>Superficie Útil: 54,52 m²</li>\r\n \t<li>Terraza: 5,36 m²</li>\r\n \t<li class=\"des-bold\">TOTAL 59,88 m²</li>\r\n</ul>", "Nombre": "Depto. 59,88 M2 totales", "PrecioDesde": 3340.0, "Dormitorios": 2, "Banos": 1, "SuperficieTotal": 59.88, "SuperficieUtil": 54.52, "Orientacion": "", "Imagenes": ["n_wm_2017071748262059400.png"], "ImagenesSmall": ["s_wm_2017071748262059400.png"], "Propiedades": [], "HayAlgunaPublicada": false, "TextoPlantaSeleccion": "2 Dorm., 1 baño", "Identificador": "86778756-610b-46ad-a7ea-1daa29096ead"}, {"Tipo": "Depto. 59,88 M2 totales", "Descripcion": "<p class=\"des-bold\">Departamento:</p>\r\n\r\n<ul>\r\n \t<li>Superficie Útil: 54,52 m²</li>\r\n \t<li>Terraza: 5,36 m²</li>\r\n \t<li class=\"des-bold\">TOTAL 59,88 m²</li>\r\n</ul>", "Nombre": "Depto. 59,88 M2 totales", "PrecioDesde": 3340.0, "Dormitorios": 2, "Banos": 1, "SuperficieTotal": 59.88, "SuperficieUtil": 54.52, "Orientacion": "", "Imagenes": [], "ImagenesSmall": [], "Propiedades": [], "HayAlgunaPublicada": false, "TextoPlantaSeleccion": "2 Dorm., 1 baño", "Identificador": "44fca36b-1ea4-47b2-b792-81dd0f59bf9f"}, {"Tipo": "Depto. 59,88 M2 totales", "Descripcion": "<p class=\"des-bold\">Departamento:</p>\r\n\r\n<ul>\r\n \t<li>Superficie Útil: 54,52 m²</li>\r\n \t<li>Terraza: 5,36 m²</li>\r\n \t<li class=\"des-bold\">TOTAL 59,88 m²</li>\r\n</ul>", "Nombre": "Depto. 59,88 M2 totales", "PrecioDesde": 3340.0, "Dormitorios": 2, "Banos": 2, "SuperficieTotal": 59.88, "SuperficieUtil": 54.52, "Orientacion": "", "Imagenes": ["n_wm_2017121844230725963.png", "n_wm_2018010247465061249.png"], "ImagenesSmall": ["s_wm_2017121844230725963.png", "s_wm_2018010247465061249.png"], "Propiedades": [{"Nombre": "Depto. 59,88 M2 totales", "NumeroPropiedad": "Depto. 59,88 M2 totales", "NumeroPiso": 0, "MetrosTotales": "59,88", "MetrosUtiles": "54,52", "Precio": 4235.0, "Orientacion": "", "Descripcion": "<p class=\"des-bold\">Departamento:</p>\r\n\r\n<ul>\r\n \t<li>Superficie Útil: 54,52 m²</li>\r\n \t<li>Terraza: 5,36 m²</li>\r\n \t<li class=\"des-bold\">TOTAL 59,88 m²</li>\r\n</ul>", "Dormitorios": 2, "Banos": 2, "EstaPublicado": true, "Identificador": "b582eecf-95f5-40ce-8aeb-211902d7365d"}], "HayAlgunaPublicada": true, "TextoPlantaSeleccion": "2 Dorm., 2 baños", "Identificador": "b93613c0-3eb7-4f10-9af1-3d8a31d2a02e"}, {"Tipo": "Depto. 53,96 M2 totales", "Descripcion": "<p class=\"des-bold\">Departamento:</p>\r\n\r\n<ul>\r\n \t<li>Superficie Útil: 51,18 m²</li>\r\n \t<li>Terraza: 2,78 m²</li>\r\n \t<li class=\"des-bold\">TOTAL 53,96 m²</li>\r\n</ul>", "Nombre": "Depto. 53,96 M2 totales", "PrecioDesde": 3725.0, "Dormitorios": 2, "Banos": 2, "SuperficieTotal": 53.96, "SuperficieUtil": 51.18, "Orientacion": "", "Imagenes": ["n_wm_2019081302332626689.png"], "ImagenesSmall": ["s_wm_2019081302332626689.png"], "Propiedades": [], "HayAlgunaPublicada": false, "TextoPlantaSeleccion": "2 Dorm., 2 baños", "Identificador": "5d3a6606-a472-4575-86a2-8fe906050aaf"}, {"Tipo": "64,86 m2", "Descripcion": "", "Nombre": "", "PrecioDesde": 3790.0, "Dormitorios": 2, "Banos": 2, "SuperficieTotal": 64.86, "SuperficieUtil": 59.4, "Orientacion": "", "Imagenes": ["n_wm_2016050253008206609.jpg"], "ImagenesSmall": ["s_wm_2016050253008206609.jpg"], "Propiedades": [], "HayAlgunaPublicada": false, "TextoPlantaSeleccion": "2 Dorm., 2 baños", "Identificador": "9d0dde57-5b72-4244-9406-a68dbb1a459c"}, {"Tipo": "general mackenna planta 10", "Descripcion": "", "Nombre": "general mackenna planta 10", "PrecioDesde": 3840.0, "Dormitorios": 2, "Banos": 2, "SuperficieTotal": 64.86, "SuperficieUtil": 59.4, "Orientacion": "", "Imagenes": ["n_wm_2017011829153434726.jpg"], "ImagenesSmall": ["s_wm_2017011829153434726.jpg"], "Propiedades": [], "HayAlgunaPublicada": false, "TextoPlantaSeleccion": "2 Dorm., 2 baños", "Identificador": "ff9e209a-e2a1-4f14-8cb3-d5ca2d59035b"}, {"Tipo": "Dúplex General Mackenna 64,86 M2", "Descripcion": "<p class=\"des-bold\">Duplex: </p>\r\n\r\n<ul>\r\n \t<li>Superficie Útil: 59,4 m²</li>\t\t\r\n\t<li>Terraza: 5,46 m²</li>        \r\n \t<li class=\"des-bold\">TOTAL 64,86 m²</li>\r\n</ul>", "Nombre": "Dúplex General Mackenna 64,86 M2", "PrecioDesde": 3840.0, "Dormitorios": 2, "Banos": 1, "SuperficieTotal": 64.86, "SuperficieUtil": 59.4, "Orientacion": "", "Imagenes": ["n_wm_2017071748164485772.png"], "ImagenesSmall": ["s_wm_2017071748164485772.png"], "Propiedades": [], "HayAlgunaPublicada": false, "TextoPlantaSeleccion": "2 Dorm., 1 baño", "Identificador": "e5b6ec71-9ea4-4c77-aeb2-df56316f416c"}, {"Tipo": "Dúplex General Mackenna 64,86 M2", "Descripcion": "<p class=\"des-bold\">Duplex: </p>\r\n\r\n<ul>\r\n \t<li>Superficie Útil: 59,4 m²</li>\t\t\r\n\t<li>Terraza: 5,46 m²</li>        \r\n \t<li class=\"des-bold\">TOTAL 64,86 m²</li>\r\n</ul>", "Nombre": "Dúplex General Mackenna 64,86 M2", "PrecioDesde": 3840.0, "Dormitorios": 2, "Banos": 1, "SuperficieTotal": 64.86, "SuperficieUtil": 59.4, "Orientacion": "", "Imagenes": [], "ImagenesSmall": [], "Propiedades": [], "HayAlgunaPublicada": false, "TextoPlantaSeleccion": "2 Dorm., 1 baño", "Identificador": "db8b8c5e-bc5c-43b9-9372-899cc9bcda62"}, {"Tipo": "Dúplex General Mackenna 64,86 M2", "Descripcion": "<p class=\"des-bold\">Duplex:</p>\r\n\r\n<ul>\r\n \t<li>Superficie Útil: 59,4 m²</li>\r\n \t<li>Terraza: 5,46 m²</li>\r\n \t<li class=\"des-bold\">TOTAL 64,86 m²</li>\r\n</ul>", "Nombre": "Dúplex General Mackenna 64,86 M2", "PrecioDesde": 3840.0, "Dormitorios": 2, "Banos": 2, "SuperficieTotal": 64.86, "SuperficieUtil": 59.4, "Orientacion": "", "Imagenes": ["n_wm_2017121844143672635.png", "n_wm_2018010247388250117.png"], "ImagenesSmall": ["s_wm_2017121844143672635.png", "s_wm_2018010247388250117.png"], "Propiedades": [], "HayAlgunaPublicada": false, "TextoPlantaSeleccion": "2 Dorm., 2 baños", "Identificador": "a93b9446-2ade-4b01-869d-b41752e18142"}], "Programas": [{"Tipo": "26,01 m2", "Descripcion": "", "Nombre": "", "PrecioDesde": 1620.0, "Dormitorios": 1, "Banos": 1, "SuperficieTotal": 26.01, "SuperficieUtil": 26.01, "Orientacion": "", "Propiedades": [{"Nombre": "Depto. 26,01 M2 totales", "NumeroPropiedad": "Depto. 26,01 M2 totales", "NumeroPiso": 0, "MetrosTotales": "26,01", "MetrosUtiles": "26,01", "Precio": 2235.0, "Orientacion": "", "Descripcion": "<p class=\"des-bold\">Departamento:</p>\r\n\r\n<ul>\r\n \t<li>Superficie Útil: 26,0m²</li>\r\n \t<li class=\"des-bold\">TOTAL 26,01 m²</li>\r\n</ul>", "Dormitorios": 1, "Banos": 1, "EstaPublicado": true, "Identificador": "e0e124e0-3362-4b99-8d3f-968b82648171", "Imagenes": ["n_wm_2017121844185739109.png", "n_wm_2018010247426505601.png"], "ImagenesSmall": ["s_wm_2017121844185739109.png", "s_wm_2018010247426505601.png"]}, {"Nombre": "Depto. 35,00 M2 totales", "NumeroPropiedad": "Depto. 35,00 M2 totales", "NumeroPiso": 0, "MetrosTotales": "35", "MetrosUtiles": "32,18", "Precio": 3255.0, "Orientacion": "", "Descripcion": "<p class=\"des-bold\">Departamento:</p>\r\n\r\n<ul>\r\n \t<li>Superficie Útil: 32,18 m²</li>\r\n \t<li>Terraza: 2,82 m²</li>\r\n \t<li class=\"des-bold\">TOTAL 35,00 m²</li>\r\n</ul>", "Dormitorios": 1, "Banos": 1, "EstaPublicado": true, "Identificador": "92d2a656-26db-4846-8e43-593f2e7d5b76", "Imagenes": ["n_wm_2017121844207603116.png", "n_wm_2018010247444998310.png"], "ImagenesSmall": ["s_wm_2017121844207603116.png", "s_wm_2018010247444998310.png"]}], "HayAlgunaPublicada": true, "TextoProgramaSeleccion": "1 Dorm., 1 baño", "Identificador": "060a2147-6b77-4bd6-879d-fe71c1c85d2d"}, {"Tipo": "48,37 m2", "Descripcion": "", "Nombre": "", "PrecioDesde": 2560.0, "Dormitorios": 2, "Banos": 1, "SuperficieTotal": 48.37, "SuperficieUtil": 43.05, "Orientacion": "", "Propiedades": [], "HayAlgunaPublicada": false, "TextoProgramaSeleccion": "2 Dorm., 1 baño", "Identificador": "de166e45-0897-478a-9bad-1c3cdd09d6fd"}, {"Tipo": "52,39 m2", "Descripcion": "", "Nombre": "", "PrecioDesde": 2830.0, "Dormitorios": 2, "Banos": 2, "SuperficieTotal": 52.39, "SuperficieUtil": 50.05, "Orientacion": "", "Propiedades": [{"Nombre": "Depto. 59,88 M2 totales", "NumeroPropiedad": "Depto. 59,88 M2 totales", "NumeroPiso": 0, "MetrosTotales": "59,88", "MetrosUtiles": "54,52", "Precio": 4235.0, "Orientacion": "", "Descripcion": "<p class=\"des-bold\">Departamento:</p>\r\n\r\n<ul>\r\n \t<li>Superficie Útil: 54,52 m²</li>\r\n \t<li>Terraza: 5,36 m²</li>\r\n \t<li class=\"des-bold\">TOTAL 59,88 m²</li>\r\n</ul>", "Dormitorios": 2, "Banos": 2, "EstaPublicado": true, "Identificador": "b582eecf-95f5-40ce-8aeb-211902d7365d", "Imagenes": ["n_wm_2017121844230725963.png", "n_wm_2018010247465061249.png"], "ImagenesSmall": ["s_wm_2017121844230725963.png", "s_wm_2018010247465061249.png"]}], "HayAlgunaPublicada": true, "TextoProgramaSeleccion": "2 Dorm., 2 baños", "Identificador": "81314e7d-a2c2-4b9b-9711-f77289e9a100"}], "OrdenProyecto": 2, "MetrosUtiles": 26.01, "MetrosTerraza": 0.0, "MetrosConstruidos": 26.01, "MetrosTerreno": 26.01, "ProyectoEmpresaCliente": {"Id": 1, "Nombre": "Almagro", "Email": "info@almagro.cl", "Contacto": "Sala de Ventas", "Telefono": "3726666", "Descripcion": "", "Logo": "2015100806030281282.jpg", "Escliente": true, "Direccion": "Padre Mariano 277, Providencia", "ContenidoEmpresa": [{"TipoContenido": 1, "Contenido": "Inmobiliaria Almagro | TOCTOC.com", "FechaCreacion": "2016-11-28T18:25:40.82", "FechaModificacion": null}, {"TipoContenido": 2, "Contenido": "Listado completo de proyectos inmobiliarios de Inmobiliaria Almagro. Características, fotografías, precios y ubicaciones. Email y teléfono de contacto.", "FechaCreacion": "2016-11-28T18:25:40.823", "FechaModificacion": null}, {"TipoContenido": 3, "Contenido": "Inmobiliaria Almagro S.A es una sociedad anónima filial de Socovesa S.A desde agosto de 2007, aunque en el mercado inmobiliario tiene una destacada trayectoria que data desde 1977. Con grandes proyectos en departamentos y viviendas, esta empresa se ha posicionado como una de las favoritas de quienes buscan un espacio para formar una nueva vida, debido a sus altos estándares de seguridad, diseño y calidad para las familias que buscan mejorar su nivel de vida.", "FechaCreacion": "2016-11-28T18:25:40.827", "FechaModificacion": null}, {"TipoContenido": 6, "Contenido": "almagro", "FechaCreacion": "2016-11-28T18:25:40.817", "FechaModificacion": null}]}, "ProyectoEmpresaConstructora": {"Id": 1, "Nombre": "Almagro", "Email": "info@almagro.cl", "Contacto": "Sala de Ventas", "Telefono": "3726666", "Descripcion": "", "Logo": "2015100806030281282.jpg", "Escliente": true, "Direccion": "Padre Mariano 277, Providencia", "ContenidoEmpresa": [{"TipoContenido": 1, "Contenido": "Inmobiliaria Almagro | TOCTOC.com", "FechaCreacion": "2016-11-28T18:25:40.82", "FechaModificacion": null}, {"TipoContenido": 2, "Contenido": "Listado completo de proyectos inmobiliarios de Inmobiliaria Almagro. Características, fotografías, precios y ubicaciones. Email y teléfono de contacto.", "FechaCreacion": "2016-11-28T18:25:40.823", "FechaModificacion": null}, {"TipoContenido": 3, "Contenido": "Inmobiliaria Almagro S.A es una sociedad anónima filial de Socovesa S.A desde agosto de 2007, aunque en el mercado inmobiliario tiene una destacada trayectoria que data desde 1977. Con grandes proyectos en departamentos y viviendas, esta empresa se ha posicionado como una de las favoritas de quienes buscan un espacio para formar una nueva vida, debido a sus altos estándares de seguridad, diseño y calidad para las familias que buscan mejorar su nivel de vida.", "FechaCreacion": "2016-11-28T18:25:40.827", "FechaModificacion": null}, {"TipoContenido": 6, "Contenido": "almagro", "FechaCreacion": "2016-11-28T18:25:40.817", "FechaModificacion": null}]}, "ProyectoEmpresaInmobiliaria": {"Id": 1, "Nombre": "Almagro", "Email": "info@almagro.cl", "Contacto": "Sala de Ventas", "Telefono": "3726666", "Descripcion": "", "Logo": "2015100806030281282.jpg", "Escliente": true, "Direccion": "Padre Mariano 277, Providencia", "ContenidoEmpresa": [{"TipoContenido": 1, "Contenido": "Inmobiliaria Almagro | TOCTOC.com", "FechaCreacion": "2016-11-28T18:25:40.82", "FechaModificacion": null}, {"TipoContenido": 2, "Contenido": "Listado completo de proyectos inmobiliarios de Inmobiliaria Almagro. Características, fotografías, precios y ubicaciones. Email y teléfono de contacto.", "FechaCreacion": "2016-11-28T18:25:40.823", "FechaModificacion": null}, {"TipoContenido": 3, "Contenido": "Inmobiliaria Almagro S.A es una sociedad anónima filial de Socovesa S.A desde agosto de 2007, aunque en el mercado inmobiliario tiene una destacada trayectoria que data desde 1977. Con grandes proyectos en departamentos y viviendas, esta empresa se ha posicionado como una de las favoritas de quienes buscan un espacio para formar una nueva vida, debido a sus altos estándares de seguridad, diseño y calidad para las familias que buscan mejorar su nivel de vida.", "FechaCreacion": "2016-11-28T18:25:40.827", "FechaModificacion": null}, {"TipoContenido": 6, "Contenido": "almagro", "FechaCreacion": "2016-11-28T18:25:40.817", "FechaModificacion": null}]}, "ProyectoEmpresaVende": {"Id": 1, "Nombre": "Almagro", "Email": "info@almagro.cl", "Contacto": "Sala de Ventas", "Telefono": "3726666", "Descripcion": "", "Logo": "2015100806030281282.jpg", "Escliente": true, "Direccion": "Padre Mariano 277, Providencia", "ContenidoEmpresa": [{"TipoContenido": 1, "Contenido": "Inmobiliaria Almagro | TOCTOC.com", "FechaCreacion": "2016-11-28T18:25:40.82", "FechaModificacion": null}, {"TipoContenido": 2, "Contenido": "Listado completo de proyectos inmobiliarios de Inmobiliaria Almagro. Características, fotografías, precios y ubicaciones. Email y teléfono de contacto.", "FechaCreacion": "2016-11-28T18:25:40.823", "FechaModificacion": null}, {"TipoContenido": 3, "Contenido": "Inmobiliaria Almagro S.A es una sociedad anónima filial de Socovesa S.A desde agosto de 2007, aunque en el mercado inmobiliario tiene una destacada trayectoria que data desde 1977. Con grandes proyectos en departamentos y viviendas, esta empresa se ha posicionado como una de las favoritas de quienes buscan un espacio para formar una nueva vida, debido a sus altos estándares de seguridad, diseño y calidad para las familias que buscan mejorar su nivel de vida.", "FechaCreacion": "2016-11-28T18:25:40.827", "FechaModificacion": null}, {"TipoContenido": 6, "Contenido": "almagro", "FechaCreacion": "2016-11-28T18:25:40.817", "FechaModificacion": null}]}, "SolicitarDatosFaltantesUsuario": true, "CantidadUnidades": 0, "PorcentajeUnidadesDisponible": 0, "CantidadPisos": 27, "SitioWeb": "", "Imagenes": ["https://d1cfu8v5n1wsm.cloudfront.net/toctoc/fotos/20160502/563334/n_wm_2017121844043047284.jpg", "https://d1cfu8v5n1wsm.cloudfront.net/toctoc/fotos/20160502/563334/n_wm_2018010348009654596.jpg", "https://d1cfu8v5n1wsm.cloudfront.net/toctoc/fotos/20160502/563334/n_wm_2018010348017775730.jpg", "https://d1cfu8v5n1wsm.cloudfront.net/toctoc/fotos/20160502/563334/n_wm_2018010348027627250.jpg", "https://d1cfu8v5n1wsm.cloudfront.net/toctoc/fotos/20160502/563334/n_wm_2018010348037248590.jpg", "https://d1cfu8v5n1wsm.cloudfront.net/toctoc/fotos/20160502/563334/n_wm_2018010414178766043.jpg", "https://d1cfu8v5n1wsm.cloudfront.net/toctoc/fotos/20160502/563334/n_wm_2018010414201670002.jpg", "https://d1cfu8v5n1wsm.cloudfront.net/toctoc/fotos/20160502/563334/n_wm_2018010414214332135.jpg", "https://d1cfu8v5n1wsm.cloudfront.net/toctoc/fotos/20160502/563334/n_wm_2018010414257309525.jpg", "https://d1cfu8v5n1wsm.cloudfront.net/toctoc/fotos/20160502/563334/n_wm_2018010414281213632.jpg", "https://d1cfu8v5n1wsm.cloudfront.net/toctoc/fotos/20160502/563334/n_wm_2018010414296286222.jpg", "https://d1cfu8v5n1wsm.cloudfront.net/toctoc/fotos/20160502/563334/n_wm_2018010414306968228.jpg", "https://d1cfu8v5n1wsm.cloudfront.net/toctoc/fotos/20160502/563334/n_wm_2018010414333282577.jpg", "https://d1cfu8v5n1wsm.cloudfront.net/toctoc/fotos/20160502/563334/n_wm_2018010414351275799.jpg", "https://d1cfu8v5n1wsm.cloudfront.net/toctoc/fotos/20160502/563334/n_wm_2018010414367118399.jpg", "https://d1cfu8v5n1wsm.cloudfront.net/toctoc/fotos/20160502/563334/n_wm_2018010414378980438.jpg", "https://d1cfu8v5n1wsm.cloudfront.net/toctoc/fotos/20160502/563334/n_wm_2018010414389652263.jpg", "https://d1cfu8v5n1wsm.cloudfront.net/toctoc/fotos/20160502/563334/n_wm_2018010414405404991.jpg", "https://d1cfu8v5n1wsm.cloudfront.net/toctoc/fotos/20160502/563334/n_wm_2018010414419187406.jpg", "https://d1cfu8v5n1wsm.cloudfront.net/toctoc/fotos/20160502/563334/n_wm_2018010414455343586.jpg", "https://d1cfu8v5n1wsm.cloudfront.net/toctoc/fotos/20160502/563334/n_wm_2018010414474016819.jpg", "https://d1cfu8v5n1wsm.cloudfront.net/toctoc/fotos/20160502/563334/n_wm_2018010414505552219.jpg", "https://d1cfu8v5n1wsm.cloudfront.net/toctoc/fotos/20160502/563334/n_wm_2018010414521004884.jpg", "https://d1cfu8v5n1wsm.cloudfront.net/toctoc/fotos/20160502/563334/n_wm_2018010414544938977.jpg", "https://d1cfu8v5n1wsm.cloudfront.net/toctoc/fotos/20160502/563334/n_wm_2018010414575244197.jpg", "https://d1cfu8v5n1wsm.cloudfront.net/toctoc/fotos/20160502/563334/n_wm_2018010415015441149.jpg", "https://d1cfu8v5n1wsm.cloudfront.net/toctoc/fotos/20160502/563334/n_wm_2018010415031483891.jpg", "https://d1cfu8v5n1wsm.cloudfront.net/toctoc/fotos/20160502/563334/n_wm_2018010415061008954.jpg", "https://d1cfu8v5n1wsm.cloudfront.net/toctoc/fotos/20160502/563334/n_wm_2018010415084222964.jpg", "https://d1cfu8v5n1wsm.cloudfront.net/toctoc/fotos/20160502/563334/n_wm_2018010415166786138.jpg", "https://d1cfu8v5n1wsm.cloudfront.net/toctoc/fotos/20160502/563334/n_wm_2018010415223724868.jpg", "https://d1cfu8v5n1wsm.cloudfront.net/toctoc/fotos/20160502/563334/n_wm_2018010415246098469.jpg", "https://d1cfu8v5n1wsm.cloudfront.net/toctoc/fotos/20160502/563334/n_wm_2019082010505726022.jpg", "https://d1cfu8v5n1wsm.cloudfront.net/toctoc/fotos/20160502/563334/n_wm_2019082010516332724.jpg", "https://d1cfu8v5n1wsm.cloudfront.net/toctoc/fotos/20160502/563334/n_wm_2019082010526942331.jpg", "https://d1cfu8v5n1wsm.cloudfront.net/toctoc/fotos/20160502/563334/n_wm_2019082010537393148.jpg", "https://d1cfu8v5n1wsm.cloudfront.net/toctoc/fotos/20160502/563334/n_wm_2019082010548781276.jpg", "https://d1cfu8v5n1wsm.cloudfront.net/toctoc/fotos/20160502/563334/n_wm_2019082010559545693.jpg", "https://d1cfu8v5n1wsm.cloudfront.net/toctoc/fotos/20160502/563334/n_wm_2019082010571089628.jpg"], "ImagenesVista": [{"Id": "65e8551f-2a69-49bb-a447-b5ad9525387a", "Orden": 0, "Ruta": "https://d1cfu8v5n1wsm.cloudfront.net/toctoc/fotos/20160502/563334/n_wm_2017121844043047284.jpg"}, {"Id": "7bdacf57-7bdb-4691-b180-04d8a242fe47", "Orden": 4, "Ruta": "https://d1cfu8v5n1wsm.cloudfront.net/toctoc/fotos/20160502/563334/n_wm_2018010348009654596.jpg"}, {"Id": "d777ec57-48e6-4aa8-b208-f0d2ba105e3c", "Orden": 5, "Ruta": "https://d1cfu8v5n1wsm.cloudfront.net/toctoc/fotos/20160502/563334/n_wm_2018010348017775730.jpg"}, {"Id": "be59d66e-d1bd-4094-8d81-3b9a8ae49ae6", "Orden": 6, "Ruta": "https://d1cfu8v5n1wsm.cloudfront.net/toctoc/fotos/20160502/563334/n_wm_2018010348027627250.jpg"}, {"Id": "a0149a1b-1ef4-465f-954a-109380cc64fe", "Orden": 7, "Ruta": "https://d1cfu8v5n1wsm.cloudfront.net/toctoc/fotos/20160502/563334/n_wm_2018010348037248590.jpg"}, {"Id": "db164930-d84d-4141-9caa-fabed494fc22", "Orden": 7, "Ruta": "https://d1cfu8v5n1wsm.cloudfront.net/toctoc/fotos/20160502/563334/n_wm_2018010414178766043.jpg"}, {"Id": "361db4ab-3186-437f-a41c-a6f1e613aa9d", "Orden": 8, "Ruta": "https://d1cfu8v5n1wsm.cloudfront.net/toctoc/fotos/20160502/563334/n_wm_2018010414201670002.jpg"}, {"Id": "277dd3da-4efc-4a87-ac1a-534e2ce332eb", "Orden": 9, "Ruta": "https://d1cfu8v5n1wsm.cloudfront.net/toctoc/fotos/20160502/563334/n_wm_2018010414214332135.jpg"}, {"Id": "71c08edc-1a51-4c6d-a8dc-8030079298e3", "Orden": 10, "Ruta": "https://d1cfu8v5n1wsm.cloudfront.net/toctoc/fotos/20160502/563334/n_wm_2018010414257309525.jpg"}, {"Id": "9b4f1228-b406-4ed6-968c-d7ee5ea5621f", "Orden": 11, "Ruta": "https://d1cfu8v5n1wsm.cloudfront.net/toctoc/fotos/20160502/563334/n_wm_2018010414281213632.jpg"}, {"Id": "4bc25106-bef7-482e-a92b-1eb517dcebf6", "Orden": 12, "Ruta": "https://d1cfu8v5n1wsm.cloudfront.net/toctoc/fotos/20160502/563334/n_wm_2018010414296286222.jpg"}, {"Id": "baf539f4-bcf9-46eb-9b05-e0ae305785ce", "Orden": 13, "Ruta": "https://d1cfu8v5n1wsm.cloudfront.net/toctoc/fotos/20160502/563334/n_wm_2018010414306968228.jpg"}, {"Id": "68afdb22-15b6-4048-bfe3-9982a3933e97", "Orden": 14, "Ruta": "https://d1cfu8v5n1wsm.cloudfront.net/toctoc/fotos/20160502/563334/n_wm_2018010414333282577.jpg"}, {"Id": "801cd8dd-f427-4e2a-a3d2-d232795c653e", "Orden": 15, "Ruta": "https://d1cfu8v5n1wsm.cloudfront.net/toctoc/fotos/20160502/563334/n_wm_2018010414351275799.jpg"}, {"Id": "1d6dafec-2afc-4d3c-8eae-a07ff4f21bf2", "Orden": 16, "Ruta": "https://d1cfu8v5n1wsm.cloudfront.net/toctoc/fotos/20160502/563334/n_wm_2018010414367118399.jpg"}, {"Id": "b8590b05-3a43-4e81-b22a-5bce3c14af2e", "Orden": 17, "Ruta": "https://d1cfu8v5n1wsm.cloudfront.net/toctoc/fotos/20160502/563334/n_wm_2018010414378980438.jpg"}, {"Id": "19189b04-0584-4c53-b8a0-7373f8ed6672", "Orden": 18, "Ruta": "https://d1cfu8v5n1wsm.cloudfront.net/toctoc/fotos/20160502/563334/n_wm_2018010414389652263.jpg"}, {"Id": "b86cb4ae-98ac-4109-a57e-a8a5ed2dd19e", "Orden": 19, "Ruta": "https://d1cfu8v5n1wsm.cloudfront.net/toctoc/fotos/20160502/563334/n_wm_2018010414405404991.jpg"}, {"Id": "14b09669-4ebf-4d08-831a-8c9d24a301d6", "Orden": 20, "Ruta": "https://d1cfu8v5n1wsm.cloudfront.net/toctoc/fotos/20160502/563334/n_wm_2018010414419187406.jpg"}, {"Id": "7cf1ab87-a729-4e0f-8053-78c8e29fedbd", "Orden": 21, "Ruta": "https://d1cfu8v5n1wsm.cloudfront.net/toctoc/fotos/20160502/563334/n_wm_2018010414455343586.jpg"}, {"Id": "06adda9c-9622-43f9-922b-91bd6fb01ee6", "Orden": 22, "Ruta": "https://d1cfu8v5n1wsm.cloudfront.net/toctoc/fotos/20160502/563334/n_wm_2018010414474016819.jpg"}, {"Id": "b4fd9203-54c1-4b43-9d45-8fc1924e3921", "Orden": 23, "Ruta": "https://d1cfu8v5n1wsm.cloudfront.net/toctoc/fotos/20160502/563334/n_wm_2018010414505552219.jpg"}, {"Id": "fe7c59ba-186b-43b5-9de6-2656cc7939a2", "Orden": 24, "Ruta": "https://d1cfu8v5n1wsm.cloudfront.net/toctoc/fotos/20160502/563334/n_wm_2018010414521004884.jpg"}, {"Id": "5ef8773a-c9dd-4a42-b945-c745a126861e", "Orden": 25, "Ruta": "https://d1cfu8v5n1wsm.cloudfront.net/toctoc/fotos/20160502/563334/n_wm_2018010414544938977.jpg"}, {"Id": "c40288a3-d7d2-4047-83b9-9de130830bae", "Orden": 26, "Ruta": "https://d1cfu8v5n1wsm.cloudfront.net/toctoc/fotos/20160502/563334/n_wm_2018010414575244197.jpg"}, {"Id": "c2ed4f97-75f9-4d5f-a6fe-037382d4f80d", "Orden": 27, "Ruta": "https://d1cfu8v5n1wsm.cloudfront.net/toctoc/fotos/20160502/563334/n_wm_2018010415015441149.jpg"}, {"Id": "50e5fe5d-9e06-416d-b011-2c70c1dfa917", "Orden": 28, "Ruta": "https://d1cfu8v5n1wsm.cloudfront.net/toctoc/fotos/20160502/563334/n_wm_2018010415031483891.jpg"}, {"Id": "01e2c734-18fc-4fd0-9c50-5167e27f4b55", "Orden": 29, "Ruta": "https://d1cfu8v5n1wsm.cloudfront.net/toctoc/fotos/20160502/563334/n_wm_2018010415061008954.jpg"}, {"Id": "5d61b4fc-946e-49b5-8538-55e4d9d24494", "Orden": 30, "Ruta": "https://d1cfu8v5n1wsm.cloudfront.net/toctoc/fotos/20160502/563334/n_wm_2018010415084222964.jpg"}, {"Id": "8be13a56-c29d-4d1b-acc2-7e757a1ae120", "Orden": 31, "Ruta": "https://d1cfu8v5n1wsm.cloudfront.net/toctoc/fotos/20160502/563334/n_wm_2018010415166786138.jpg"}, {"Id": "139af435-94f3-4e23-88ca-2a84cbbfc1f5", "Orden": 32, "Ruta": "https://d1cfu8v5n1wsm.cloudfront.net/toctoc/fotos/20160502/563334/n_wm_2018010415223724868.jpg"}, {"Id": "af068733-9eb8-46a4-8328-ddf727546179", "Orden": 33, "Ruta": "https://d1cfu8v5n1wsm.cloudfront.net/toctoc/fotos/20160502/563334/n_wm_2018010415246098469.jpg"}, {"Id": "1e32ba3c-2d99-414c-bcac-2c5648e62702", "Orden": 33, "Ruta": "https://d1cfu8v5n1wsm.cloudfront.net/toctoc/fotos/20160502/563334/n_wm_2019082010505726022.jpg"}, {"Id": "ae84da72-a157-4247-9386-aab0898b4f2f", "Orden": 34, "Ruta": "https://d1cfu8v5n1wsm.cloudfront.net/toctoc/fotos/20160502/563334/n_wm_2019082010516332724.jpg"}, {"Id": "6a38b78d-56c0-4a67-a264-eef18c112131", "Orden": 35, "Ruta": "https://d1cfu8v5n1wsm.cloudfront.net/toctoc/fotos/20160502/563334/n_wm_2019082010526942331.jpg"}, {"Id": "d54d4349-b871-4f1e-81a9-2b34cf2f1aa5", "Orden": 36, "Ruta": "https://d1cfu8v5n1wsm.cloudfront.net/toctoc/fotos/20160502/563334/n_wm_2019082010537393148.jpg"}, {"Id": "66b846f0-25cf-4709-aebf-057286b3bd5e", "Orden": 37, "Ruta": "https://d1cfu8v5n1wsm.cloudfront.net/toctoc/fotos/20160502/563334/n_wm_2019082010548781276.jpg"}, {"Id": "fe5b4b56-9c00-4c07-8231-2387faa47add", "Orden": 38, "Ruta": "https://d1cfu8v5n1wsm.cloudfront.net/toctoc/fotos/20160502/563334/n_wm_2019082010559545693.jpg"}, {"Id": "13124cd5-7489-4122-bdcc-4bca623bbcc7", "Orden": 39, "Ruta": "https://d1cfu8v5n1wsm.cloudfront.net/toctoc/fotos/20160502/563334/n_wm_2019082010571089628.jpg"}], "Id": 563334, "IdExterno": 22930, "EstaPublicada": true, "EstaEliminada": false, "IdEstadoPropiedad": 1, "IdTipoOperacion": 7, "IdTipoPropiedad": 2, "IdTipoMoneda": 2, "PrecioDesde": 2235.0, "PrecioHasta": 2235.0, "EsToctoc": 0, "PrecioUF": 2235.0, "PrecioPesos": 62726057, "PrecioDespliegue": "UF 2.235", "PrecioAlternativo": "$ 62.726.057", "TasacionToctoc": null, "OrigenTasacionToctoc": null, "SimulacionCredito": "10,7 UF/mes", "Titulo": "General Mackenna", "Observaciones": "El edificio está equipado con hall de acceso de doble altura. El cuarto piso cuenta con un patio con juegos infantiles y máquinas de ejercicio, salón de niños, salones multiuso y gimnasio equipado. En el último piso cuenta con piscina y cinco quinchos. Control con cámaras de seguridad en todos los pisos.", "DireccionCalle": "General Mackenna 1555, Santiago Centro", "DireccionDepto": "", "DireccionNumero": "", "Exactitud": 0, "Comuna": "Santiago", "Region": "Metropolitana", "TipoOperacion": "Venta Nuevo", "IdComuna": 339, "IdRegion": 13, "Latitud": "-33.433271000000", "Longitud": "-70.659824000000", "RutaContenido": "20160502", "Contacto": null, "CodigoPropiedad": null, "FechaPublicacionDespliegue": "02-05-2016", "Usuario": null, "PublicacionesSimilaresCercanas": null, "IdTipoPropiedadFamilia": 2, "IdTipoOperacionFamilia": 2, "IdManzanaReal": 509, "IdZona": 1, "PropiedadMultimedias": [], "TipoSubsidioPropiedad": null, "Destacada": 0}, "Estadistica": {"CantidadVisitas": 41453, "CantidadFavoritos": 83, "CantidadInteresados": 25124}, "TasaMoneda": {"Fecha": "2019-12-31T00:00:00", "Monto": 28309.94}, "Exitosa": true, "Mensaje": ""}, "Favorite": {"EsFavorita": false, "Exitosa": false, "Mensaje": ""}, "RutaSitioEstatico": "https://d1cfu8v5n1wsm.cloudfront.net/toctoc/", "IsAuth": false, "UriSolicitarFinanciamiento": "https://www.toctoc.com/Financiamiento/Asesor?IdPropiedad=563334&d=cabecerafija", "InformacionAdicional": {"FrasesDescripcion": ["El edificio está equipado con hall de acceso de doble altura. El cuarto piso cuenta con un patio con juegos infantiles y máquinas de ejercicio, salón de niños, salones multiuso y gimnasio equipado. En el último piso cuenta con piscina y cinco quinchos. Control con cámaras de seguridad en todos los pisos."], "FrasesAspectos": []}, "Simular": {"PrecioMontoCredito": "2.011,5", "PrecioUF": "2.235"}, "InformacionBasica": {"Arquitecto": "sin información", "Constructora": "Almagro", "Inmobiliaria": "Almagro", "SimulacionCredito": "10,7 UF/mes", "Entrega": "1 Semestre 2019", "M2": "útil", "DormitoriosText": "Dormitorio", "Dormitorios": 1, "Baños": 1, "BañosText": "Baño", "DireccionCalle": "General Mackenna 1555, Santiago Centro", "DireccionNumero": "", "Comuna": "Santiago", "Region": "Metropolitana", "MetrosUtiles": "26,01", "CantidadUnidades": 0, "PorcentajeUnidadesDisponible": "", "CantidadPisos": 27}, "Rutas": {"RutaSitioEstatico": "https://d1cfu8v5n1wsm.cloudfront.net/toctoc/", "RutaIcoCargando": "https://d1cfu8v5n1wsm.cloudfront.net/toctoc/img/cargando32x32.gif", "RutaIconoPropiedad": "https://d1cfu8v5n1wsm.cloudfront.net/toctoc/img/ico_propiedades/ico_Venta_Edificio_nuevas.png", "RutaApiEntorno": "https://apientornotoctoc.toctoc.com/api/2.0/", "RutaApiGoogle": "https://maps.googleapis.com/maps/api/js?language=es&region=CL&key=AIzaSyD6YAjL2nNl_PpP4T5vfezNqqSR84DzYS0&libraries=places,drawing,visualization&channel=MapasFichaPropiedad", "RutaBundlesMapaCalor": "https://www.toctoc.com/bundles/mapaCalor-20191111", "RutaBundlesEntornoFichas": "https://www.toctoc.com/bundles/entornoFichas-20191111", "RutaBundlesIonRangeSlider": "https://www.toctoc.com/bundles/ionRangeSlider-20191111", "RutaBundlesIonRangeSliderModern": "https://www.toctoc.com/styles/ionRangeSliderModern-20191111", "RutaBundlesZonasHomogeneas": "https://www.toctoc.com/bundles/zonasHomogeneas-20191111"}, "EsHabitacional": true}